p52/__init__.py
p52/compiler.py
p52/reloader.py
p52/sketchClass.py
p52/viewer.py
p52/static/allDefinition.py
p52/static/index.html
p52/static/p5definition.py
p52/updater/generate_definition.py
p52/updater/updater.py
p52/utils/__init__.py
p52/utils/p52.py
p52/utils/utils.py
p5two-0.0.2.dist-info/METADATA
p5two-0.0.2.dist-info/WHEEL
p5two-0.0.2.dist-info/top_level.txt
p5two-0.0.2.dist-info/RECORD
