Metadata-Version: 2.1
Name: p5two
Version: 0.0.2
Summary: Automatically launch p5js sketches written in python
Project-URL: Homepage, https://github.com/lorenzoferrone/p52
Keywords: p5js,generative art,creative coding
Requires-Python: >=3.8
Requires-Dist: pywebview
Requires-Dist: transcrypt
Requires-Dist: websockets
Requires-Dist: watchdog
